{
  "project_info": {
    "project_number": "91362967016",
    "project_id": "batterysales-b7972",
    "storage_bucket": "batterysales-b7972.firebasestorage.app"
  },
  "client": [
    {
      "client_info": {
        "mobilesdk_app_id": "1:91362967016:android:0c08c3c339b86533a4385d",
        "android_client_info": {
          "package_name": "com.batterysales"
        }
      },
      "oauth_client": [],
      "api_key": [
        {
          "current_key": "AIzaSyAouDM3y_4St7RToxtTTXH0JTk56Yzb33Q"
        }
      ],
      "services": {
        "appinvite_service": {
          "other_platform_oauth_client": []
        }
      }
    }
  ],
  "configuration_version": "1"
}